fpga/frequency_counter.v
`default_nettype none	
`timescale 1ns/1ps

module frequency_counter #(
	parameter UPDATE_PERIOD = 1200 - 1,
	parameter BITS = 12
)
(
	input wire 				clk,
	input wire 				reset,
	input wire 				signal,

	input wire [BITS-1:0] 	period,
	input wire 				period_load,

	output wire [6:0] 		segments,
	output wire 			digit, 

	// debug wires
	output wire [1:0] 		dbg_state,		// state machine 
	output wire [2:0] 		dbg_clk_count, 	// top 3 bits of clk counter
	output wire [2:0] 		dbg_edge_count
);
	
	// debug assigns
	assign dbg_state = state;
	assign dbg_clk_count = clk_counter[BITS-1:BITS-3];
	assign dbg_edge_count = edge_counter[6:4];

	reg [BITS-1:0] update_period; // holds the number of edges for frequency measurement

	reg [6:0] edge_counter; // 2^7 is 128, can count up to 99

	reg [BITS-1:0] clk_counter; // keeps track of clocks in the counting period

	reg [3:0] unit_count, ten_count;

	reg update_digits; // toggles the loading signal for the seven pmod display

	wire leading_edge_detect;

	edge_detect edge_detect0(.signal(signal), .clk(clk), .leading_edge_detect(leading_edge_detect));

	always @(posedge clk) begin
		if (reset) 
			update_period <= UPDATE_PERIOD;
		else if (period_load) 
			update_period <= period; // sets a new period when period_load is high
	end

	// STATE machine register, holds 3 states
	reg [1:0] state;

	localparam STATE_COUNT	= 0;
	localparam STATE_TENS 	= 1;
	localparam STATE_UNITS 	= 2;

	always @(posedge clk) begin
		if (reset) begin
			clk_counter 	<= 0;
			edge_counter 	<= 0;
			unit_count	 	<= 0;
			ten_count 		<= 0;
			update_digits 	<= 0;
			state 			<= STATE_COUNT;

		end else begin
			case(state)
				STATE_COUNT : begin
					update_digits 	<= 0;
					clk_counter 	<= clk_counter + 1'b1;

					if(leading_edge_detect) 
						edge_counter <= edge_counter + 1'b1;

					if(clk_counter >= update_period) begin
						clk_counter <= 0; 
						unit_count 	<= 0; 
						ten_count	<= 0; 
						state 		<= STATE_TENS; 
					end
				end

				STATE_TENS : begin
					if (edge_counter < 7'd10)
						state <= STATE_UNITS;
					else begin
						edge_counter <= edge_counter - 7'd10;
						ten_count <= ten_count + 1'b1;
					end
				end

				STATE_UNITS : begin
					unit_count 		<= edge_counter;
					update_digits	<= 1'b1;
					edge_counter 	<= 0;
					state 			<= STATE_COUNT;
				end

				default : state <= STATE_COUNT;
				
			endcase			
		end
	end

	seven_segment seven_segment0(.clk(clk), .reset(reset), .ten_count(ten_count), .unit_count(unit_count), .load(update_digits), .segments(segments), .digit(digit));

endmodule

module edge_detect (
    input wire signal,
    input wire clk,
    output wire leading_edge_detect
);

    reg q0, q1, q2;

    always @(posedge clk) begin
       q0 <= signal;
       q1 <= q0;
       q2 <= q1;
    end

    assign leading_edge_detect = q1 & (q2 != q1);   // leaving the leading edges

endmodule

module seven_segment (

    input wire 			clk,
    input wire  		reset,
    input wire  		load,
    input wire [3:0]    ten_count,
    input wire [3:0] 	unit_count,
    output reg [6:0] 	segments,
    output reg			digit    	// digit selector
);

    reg [3:0] ten_count_reg, unit_count_reg;
    wire [3:0] decode;

    always @(posedge clk) begin
		if(reset) begin
			ten_count_reg <= 0;
			unit_count_reg <= 0;
			digit <= 0;
		end else begin
			if(load) begin
				ten_count_reg  <= ten_count;
				unit_count_reg <= unit_count;
			end

			digit <= !digit; 

		end
    end 

    assign decode = digit ? ten_count_reg: unit_count_reg;

    // why is this indented?

   	always @(*) begin
            case(decode)
            //                7654321
            0:  segments = 7'b0111111;
            1:  segments = 7'b0000110;
            2:  segments = 7'b1011011;
            3:  segments = 7'b1001111;
            4:  segments = 7'b1100110;
            5:  segments = 7'b1101101;
            6:  segments = 7'b1111100;
            7:  segments = 7'b0000111;
            8:  segments = 7'b1111111;
            9:  segments = 7'b1100111;
            default:    
                segments = 7'b0000000;
            endcase
	end


endmodule

frequency_counter.vcd
$date
	Fri May 24 01:32:14 2024
$end
$version
	Icarus Verilog
$end
$timescale
	1ps
$end
$scope module frequency_counter $end
$var wire 1 ! clk $end
$var wire 2 " dbg_state [1:0] $end
$var wire 12 # period [11:0] $end
$var wire 1 $ period_load $end
$var wire 1 % reset $end
$var wire 1 & signal $end
$var wire 7 ' segments [6:0] $end
$var wire 1 ( leading_edge_detect $end
$var wire 1 ) digit $end
$var wire 3 * dbg_edge_count [2:0] $end
$var wire 3 + dbg_clk_count [2:0] $end
$var parameter 32 , BITS $end
$var parameter 32 - STATE_COUNT $end
$var parameter 32 . STATE_TENS $end
$var parameter 32 / STATE_UNITS $end
$var parameter 33 0 UPDATE_PERIOD $end
$var reg 12 1 clk_counter [11:0] $end
$var reg 7 2 edge_counter [6:0] $end
$var reg 2 3 state [1:0] $end
$var reg 4 4 ten_count [3:0] $end
$var reg 4 5 unit_count [3:0] $end
$var reg 1 6 update_digits $end
$var reg 12 7 update_period [11:0] $end
$scope module edge_detect0 $end
$var wire 1 ! clk $end
$var wire 1 ( leading_edge_detect $end
$var wire 1 & signal $end
$var reg 1 8 q0 $end
$var reg 1 9 q1 $end
$var reg 1 : q2 $end
$upscope $end
$scope module seven_segment0 $end
$var wire 1 ! clk $end
$var wire 1 6 load $end
$var wire 1 % reset $end
$var wire 4 ; ten_count [3:0] $end
$var wire 4 < unit_count [3:0] $end
$var wire 4 = decode [3:0] $end
$var reg 1 ) digit $end
$var reg 7 > segments [6:0] $end
$var reg 4 ? ten_count_reg [3:0] $end
$var reg 4 @ unit_count_reg [3:0] $end
$upscope $end
$upscope $end
$enddefinitions $end
$comment Show the parameter values. $end
$dumpall
b10010101111 0
b10 /
b1 .
b0 -
b1100 ,
$end
#0
$dumpvars
b0 @
b0 ?
b111111 >
b0 =
b0 <
b0 ;
x:
x9
z8
b10010101111 7
06
b0 5
b0 4
b0 3
b0 2
b0 1
b0 +
b0 *
0)
x(
b111111 '
z&
1%
0$
bz #
b0 "
1!
$end
#41665
0!
#83330
z9
1!
#124995
0!
#166660
z:
1!
#208325
0!
#249990
1!
#291655
0!
#333320
0%
1!
#374985
0!
#416650
b1 1
1)
1!
#458315
0!
#499980
0)
b10 1
1!
#541645
0!
#583310
b11 1
1)
1!
#624975
0!
#666640
0)
b100 1
1!
#708305
0!
#749970
b10010101111 #
1$
b101 1
1)
1!
#791635
0!
#833300
0$
0)
b110 1
1!
#874965
0!
#916630
1&
b111 1
1)
1!
#958295
0!
#999960
18
0)
b1000 1
1!
#1041625
0!
#1083290
b1001 1
1)
19
1!
#1124955
0!
#1166620
0(
1:
0)
b1010 1
1!
#1208285
0!
#1249950
b1011 1
1)
1!
#1291615
0!
#1333280
0)
b1100 1
1!
#1374945
0!
#1416610
b1101 1
1)
1!
#1458275
0!
#1499940
0)
b1110 1
1!
#1541605
0!
#1583270
b1111 1
1)
1!
#1624935
0!
#1666600
0)
b10000 1
1!
#1708265
0!
#1749930
b10001 1
1)
1!
#1791595
0!
#1833260
0)
b10010 1
1!
#1874925
0!
#1916590
b10011 1
1)
1!
#1958255
0!
#1999920
0)
b10100 1
1!
#2041585
0!
#2083250
b10101 1
1)
1!
#2124915
0!
#2166580
0)
b10110 1
1!
#2208245
0!
#2249910
b10111 1
1)
1!
#2291575
0!
#2333240
0)
b11000 1
1!
#2374905
0!
#2416570
b11001 1
1)
1!
#2458235
0!
#2499900
0)
b11010 1
1!
#2541565
0!
#2583230
b11011 1
1)
1!
#2624895
0!
#2666560
0)
b11100 1
1!
#2708225
0!
#2749890
b11101 1
1)
1!
#2791555
0!
#2833220
0)
b11110 1
1!
#2874885
0!
#2916550
b11111 1
1)
1!
#2958215
0!
#2999880
0)
b100000 1
1!
#3041545
0!
#3083210
b100001 1
1)
1!
#3124875
0!
#3166540
0)
b100010 1
1!
#3208205
0!
#3249870
b100011 1
1)
1!
#3291535
0!
#3333200
0)
b100100 1
1!
#3374865
0!
#3416530
b100101 1
1)
1!
#3458195
0!
#3499860
0)
b100110 1
1!
#3541525
0!
#3583190
b100111 1
1)
1!
#3624855
0!
#3666520
0)
b101000 1
1!
#3708185
0!
#3749850
b101001 1
1)
1!
#3791515
0!
#3833180
0)
b101010 1
1!
#3874845
0!
#3916510
b101011 1
1)
1!
#3958175
0!
#3999840
0)
b101100 1
1!
#4041505
0!
#4083170
b101101 1
1)
1!
#4124835
0!
#4166500
0)
b101110 1
1!
#4208165
0!
#4249830
b101111 1
1)
1!
#4291495
0!
#4333160
0)
b110000 1
1!
#4374825
0!
#4416490
b110001 1
1)
1!
#4458155
0!
#4499820
0)
b110010 1
1!
#4541485
0!
#4583150
b110011 1
1)
1!
#4624815
0!
#4666480
0)
b110100 1
1!
#4708145
0!
#4749810
b110101 1
1)
1!
#4791475
0!
#4833140
0)
b110110 1
1!
#4874805
0!
#4916470
b110111 1
1)
1!
#4958135
0!
#4999800
0)
b111000 1
1!
#5041465
0!
#5083130
b111001 1
1)
1!
#5124795
0!
#5166460
0)
b111010 1
1!
#5208125
0!
#5249790
b111011 1
1)
1!
#5291455
0!
#5333120
0)
b111100 1
1!
#5374785
0!
#5416450
b111101 1
1)
1!
#5458115
0!
#5499780
0)
b111110 1
1!
#5541445
0!
#5583110
b111111 1
1)
1!
#5624775
0!
#5666440
0)
b1000000 1
1!
#5708105
0!
#5749770
b1000001 1
1)
1!
#5791435
0!
#5833100
0)
b1000010 1
1!
#5874765
0!
#5916430
b1000011 1
1)
1!
#5916630
0&
#5958095
0!
#5999760
08
0)
b1000100 1
1!
#6041425
0!
#6083090
b1000101 1
1)
09
1!
#6124755
0!
#6166420
0:
0)
b1000110 1
1!
#6208085
0!
#6249750
b1000111 1
1)
1!
#6291415
0!
#6333080
0)
b1001000 1
1!
#6374745
0!
#6416410
b1001001 1
1)
1!
#6458075
0!
#6499740
0)
b1001010 1
1!
#6541405
0!
#6583070
b1001011 1
1)
1!
#6624735
0!
#6666400
0)
b1001100 1
1!
#6708065
0!
#6749730
b1001101 1
1)
1!
#6791395
0!
#6833060
0)
b1001110 1
1!
#6874725
0!
#6916390
b1001111 1
1)
1!
#6958055
0!
#6999720
0)
b1010000 1
1!
#7041385
0!
#7083050
b1010001 1
1)
1!
#7124715
0!
#7166380
0)
b1010010 1
1!
#7208045
0!
#7249710
b1010011 1
1)
1!
#7291375
0!
#7333040
0)
b1010100 1
1!
#7374705
0!
#7416370
b1010101 1
1)
1!
#7458035
0!
#7499700
0)
b1010110 1
1!
#7541365
0!
#7583030
b1010111 1
1)
1!
#7624695
0!
#7666360
0)
b1011000 1
1!
#7708025
0!
#7749690
b1011001 1
1)
1!
#7791355
0!
#7833020
0)
b1011010 1
1!
#7874685
0!
#7916350
b1011011 1
1)
1!
#7958015
0!
#7999680
0)
b1011100 1
1!
#8041345
0!
#8083010
b1011101 1
1)
1!
#8124675
0!
#8166340
0)
b1011110 1
1!
#8208005
0!
#8249670
b1011111 1
1)
1!
#8291335
0!
#8333000
0)
b1100000 1
1!
#8374665
0!
#8416330
b1100001 1
1)
1!
#8457995
0!
#8499660
0)
b1100010 1
1!
#8541325
0!
#8582990
b1100011 1
1)
1!
#8624655
0!
#8666320
0)
b1100100 1
1!
#8707985
0!
#8749650
b1100101 1
1)
1!
#8791315
0!
#8832980
0)
b1100110 1
1!
#8874645
0!
#8916310
b1100111 1
1)
1!
#8957975
0!
#8999640
0)
b1101000 1
1!
#9041305
0!
#9082970
b1101001 1
1)
1!
#9124635
0!
#9166300
0)
b1101010 1
1!
#9207965
0!
#9249630
b1101011 1
1)
1!
#9291295
0!
#9332960
0)
b1101100 1
1!
#9374625
0!
#9416290
b1101101 1
1)
1!
#9457955
0!
#9499620
0)
b1101110 1
1!
#9541285
0!
#9582950
b1101111 1
1)
1!
#9624615
0!
#9666280
0)
b1110000 1
1!
#9707945
0!
#9749610
b1110001 1
1)
1!
#9791275
0!
#9832940
0)
b1110010 1
1!
#9874605
0!
#9916270
b1110011 1
1)
1!
#9957935
0!
#9999600
0)
b1110100 1
1!
#10041265
0!
#10082930
b1110101 1
1)
1!
#10124595
0!
#10166260
0)
b1110110 1
1!
#10207925
0!
#10249590
b1110111 1
1)
1!
#10291255
0!
#10332920
0)
b1111000 1
1!
#10374585
0!
#10416250
b1111001 1
1)
1!
#10457915
0!
#10499580
0)
b1111010 1
1!
#10541245
0!
#10582910
b1111011 1
1)
1!
#10624575
0!
#10666240
0)
b1111100 1
1!
#10707905
0!
#10749570
b1111101 1
1)
1!
#10791235
0!
#10832900
0)
b1111110 1
1!
#10874565
0!
#10916230
b1111111 1
1)
1!
#10916630
1&
#10957895
0!
#10999560
18
0)
b10000000 1
1!
#11041225
0!
#11082890
1(
b10000001 1
1)
19
1!
#11124555
0!
#11166220
0(
1:
0)
b1 2
b10000010 1
1!
#11207885
0!
#11249550
b10000011 1
1)
1!
#11291215
0!
#11332880
0)
b10000100 1
1!
#11374545
0!
#11416210
b10000101 1
1)
1!
#11457875
0!
#11499540
0)
b10000110 1
1!
#11541205
0!
#11582870
b10000111 1
1)
1!
#11624535
0!
#11666200
0)
b10001000 1
1!
#11707865
0!
#11749530
b10001001 1
1)
1!
#11791195
0!
#11832860
0)
b10001010 1
1!
#11874525
0!
#11916190
b10001011 1
1)
1!
#11957855
0!
#11999520
0)
b10001100 1
1!
#12041185
0!
#12082850
b10001101 1
1)
1!
#12124515
0!
#12166180
0)
b10001110 1
1!
#12207845
0!
#12249510
b10001111 1
1)
1!
#12291175
0!
#12332840
0)
b10010000 1
1!
#12374505
0!
#12416170
b10010001 1
1)
1!
#12457835
0!
#12499500
0)
b10010010 1
1!
#12541165
0!
#12582830
b10010011 1
1)
1!
#12624495
0!
#12666160
0)
b10010100 1
1!
#12707825
0!
#12749490
b10010101 1
1)
1!
#12791155
0!
#12832820
0)
b10010110 1
1!
#12874485
0!
#12916150
b10010111 1
1)
1!
#12957815
0!
#12999480
0)
b10011000 1
1!
#13041145
0!
#13082810
b10011001 1
1)
1!
#13124475
0!
#13166140
0)
b10011010 1
1!
#13207805
0!
#13249470
b10011011 1
1)
1!
#13291135
0!
#13332800
0)
b10011100 1
1!
#13374465
0!
#13416130
b10011101 1
1)
1!
#13457795
0!
#13499460
0)
b10011110 1
1!
#13541125
0!
#13582790
b10011111 1
1)
1!
#13624455
0!
#13666120
0)
b10100000 1
1!
#13707785
0!
#13749450
b10100001 1
1)
1!
#13791115
0!
#13832780
0)
b10100010 1
1!
#13874445
0!
#13916110
b10100011 1
1)
1!
#13957775
0!
#13999440
0)
b10100100 1
1!
#14041105
0!
#14082770
b10100101 1
1)
1!
#14124435
0!
#14166100
0)
b10100110 1
1!
#14207765
0!
#14249430
b10100111 1
1)
1!
#14291095
0!
#14332760
0)
b10101000 1
1!
#14374425
0!
#14416090
b10101001 1
1)
1!
#14457755
0!
#14499420
0)
b10101010 1
1!
#14541085
0!
#14582750
b10101011 1
1)
1!
#14624415
0!
#14666080
0)
b10101100 1
1!
#14707745
0!
#14749410
b10101101 1
1)
1!
#14791075
0!
#14832740
0)
b10101110 1
1!
#14874405
0!
#14916070
b10101111 1
1)
1!
#14957735
0!
#14999400
0)
b10110000 1
1!
#15041065
0!
#15082730
b10110001 1
1)
1!
#15124395
0!
#15166060
0)
b10110010 1
1!
#15207725
0!
#15249390
b10110011 1
1)
1!
#15291055
0!
#15332720
0)
b10110100 1
1!
#15374385
0!
#15416050
b10110101 1
1)
1!
#15457715
0!
#15499380
0)
b10110110 1
1!
#15541045
0!
#15582710
b10110111 1
1)
1!
#15624375
0!
#15666040
0)
b10111000 1
1!
#15707705
0!
#15749370
b10111001 1
1)
1!
#15791035
0!
#15832700
0)
b10111010 1
1!
#15874365
0!
#15916030
b10111011 1
1)
1!
#15916630
0&
#15957695
0!
#15999360
08
0)
b10111100 1
1!
#16041025
0!
#16082690
b10111101 1
1)
09
1!
#16124355
0!
#16166020
0:
0)
b10111110 1
1!
#16207685
0!
#16249350
b10111111 1
1)
1!
#16291015
0!
#16332680
0)
b11000000 1
1!
#16374345
0!
#16416010
b11000001 1
1)
1!
#16457675
0!
#16499340
0)
b11000010 1
1!
#16541005
0!
#16582670
b11000011 1
1)
1!
#16624335
0!
#16666000
0)
b11000100 1
1!
#16707665
0!
#16749330
b11000101 1
1)
1!
#16790995
0!
#16832660
0)
b11000110 1
1!
#16874325
0!
#16915990
b11000111 1
1)
1!
#16957655
0!
#16999320
0)
b11001000 1
1!
#17040985
0!
#17082650
b11001001 1
1)
1!
#17124315
0!
#17165980
0)
b11001010 1
1!
#17207645
0!
#17249310
b11001011 1
1)
1!
#17290975
0!
#17332640
0)
b11001100 1
1!
#17374305
0!
#17415970
b11001101 1
1)
1!
#17457635
0!
#17499300
0)
b11001110 1
1!
#17540965
0!
#17582630
b11001111 1
1)
1!
#17624295
0!
#17665960
0)
b11010000 1
1!
#17707625
0!
#17749290
b11010001 1
1)
1!
#17790955
0!
#17832620
0)
b11010010 1
1!
#17874285
0!
#17915950
b11010011 1
1)
1!
#17957615
0!
#17999280
0)
b11010100 1
1!
#18040945
0!
#18082610
b11010101 1
1)
1!
#18124275
0!
#18165940
0)
b11010110 1
1!
#18207605
0!
#18249270
b11010111 1
1)
1!
#18290935
0!
#18332600
0)
b11011000 1
1!
#18374265
0!
#18415930
b11011001 1
1)
1!
#18457595
0!
#18499260
0)
b11011010 1
1!
#18540925
0!
#18582590
b11011011 1
1)
1!
#18624255
0!
#18665920
0)
b11011100 1
1!
#18707585
0!
#18749250
b11011101 1
1)
1!
#18790915
0!
#18832580
0)
b11011110 1
1!
#18874245
0!
#18915910
b11011111 1
1)
1!
#18957575
0!
#18999240
0)
b11100000 1
1!
#19040905
0!
#19082570
b11100001 1
1)
1!
#19124235
0!
#19165900
0)
b11100010 1
1!
#19207565
0!
#19249230
b11100011 1
1)
1!
#19290895
0!
#19332560
0)
b11100100 1
1!
#19374225
0!
#19415890
b11100101 1
1)
1!
#19457555
0!
#19499220
0)
b11100110 1
1!
#19540885
0!
#19582550
b11100111 1
1)
1!
#19624215
0!
#19665880
0)
b11101000 1
1!
#19707545
0!
#19749210
b11101001 1
1)
1!
#19790875
0!
#19832540
0)
b11101010 1
1!
#19874205
0!
#19915870
b11101011 1
1)
1!
#19957535
0!
#19999200
0)
b11101100 1
1!
#20040865
0!
#20082530
b11101101 1
1)
1!
#20124195
0!
#20165860
0)
b11101110 1
1!
#20207525
0!
#20249190
b11101111 1
1)
1!
#20290855
0!
#20332520
0)
b11110000 1
1!
#20374185
0!
#20415850
b11110001 1
1)
1!
#20457515
0!
#20499180
0)
b11110010 1
1!
#20540845
0!
#20582510
b11110011 1
1)
1!
#20624175
0!
#20665840
0)
b11110100 1
1!
#20707505
0!
#20749170
b11110101 1
1)
1!
#20790835
0!
#20832500
0)
b11110110 1
1!
#20874165
0!
#20915830
b11110111 1
1)
1!
#20916630
1&
#20957495
0!
#20999160
18
0)
b11111000 1
1!
#21040825
0!
#21082490
1(
b11111001 1
1)
19
1!
#21124155
0!
#21165820
0(
1:
0)
b10 2
b11111010 1
1!
#21207485
0!
#21249150
b11111011 1
1)
1!
#21290815
0!
#21332480
0)
b11111100 1
1!
#21374145
0!
#21415810
b11111101 1
1)
1!
#21457475
0!
#21499140
0)
b11111110 1
1!
#21540805
0!
#21582470
b11111111 1
1)
1!
#21624135
0!
#21665800
0)
b100000000 1
1!
#21707465
0!
#21749130
b100000001 1
1)
1!
#21790795
0!
#21832460
0)
b100000010 1
1!
#21874125
0!
#21915790
b100000011 1
1)
1!
#21957455
0!
#21999120
0)
b100000100 1
1!
#22040785
0!
#22082450
b100000101 1
1)
1!
#22124115
0!
#22165780
0)
b100000110 1
1!
#22207445
0!
#22249110
b100000111 1
1)
1!
#22290775
0!
#22332440
0)
b100001000 1
1!
#22374105
0!
#22415770
b100001001 1
1)
1!
#22457435
0!
#22499100
0)
b100001010 1
1!
#22540765
0!
#22582430
b100001011 1
1)
1!
#22624095
0!
#22665760
0)
b100001100 1
1!
#22707425
0!
#22749090
b100001101 1
1)
1!
#22790755
0!
#22832420
0)
b100001110 1
1!
#22874085
0!
#22915750
b100001111 1
1)
1!
#22957415
0!
#22999080
0)
b100010000 1
1!
#23040745
0!
#23082410
b100010001 1
1)
1!
#23124075
0!
#23165740
0)
b100010010 1
1!
#23207405
0!
#23249070
b100010011 1
1)
1!
#23290735
0!
#23332400
0)
b100010100 1
1!
#23374065
0!
#23415730
b100010101 1
1)
1!
#23457395
0!
#23499060
0)
b100010110 1
1!
#23540725
0!
#23582390
b100010111 1
1)
1!
#23624055
0!
#23665720
0)
b100011000 1
1!
#23707385
0!
#23749050
b100011001 1
1)
1!
#23790715
0!
#23832380
0)
b100011010 1
1!
#23874045
0!
#23915710
b100011011 1
1)
1!
#23957375
0!
#23999040
0)
b100011100 1
1!
#24040705
0!
#24082370
b100011101 1
1)
1!
#24124035
0!
#24165700
0)
b100011110 1
1!
#24207365
0!
#24249030
b100011111 1
1)
1!
#24290695
0!
#24332360
0)
b100100000 1
1!
#24374025
0!
#24415690
b100100001 1
1)
1!
#24457355
0!
#24499020
0)
b100100010 1
1!
#24540685
0!
#24582350
b100100011 1
1)
1!
#24624015
0!
#24665680
0)
b100100100 1
1!
#24707345
0!
#24749010
b100100101 1
1)
1!
#24790675
0!
#24832340
0)
b100100110 1
1!
#24874005
0!
#24915670
b100100111 1
1)
1!
#24957335
0!
#24999000
0)
b100101000 1
1!
#25040665
0!
#25082330
b100101001 1
1)
1!
#25123995
0!
#25165660
0)
b100101010 1
1!
#25207325
0!
#25248990
b100101011 1
1)
1!
#25290655
0!
#25332320
0)
b100101100 1
1!
#25373985
0!
#25415650
b100101101 1
1)
1!
#25457315
0!
#25498980
0)
b100101110 1
1!
#25540645
0!
#25582310
b100101111 1
1)
1!
#25623975
0!
#25665640
0)
b100110000 1
1!
#25707305
0!
#25748970
b100110001 1
1)
1!
#25790635
0!
#25832300
0)
b100110010 1
1!
#25873965
0!
#25915630
b100110011 1
1)
1!
#25916630
0&
#25957295
0!
#25998960
08
0)
b100110100 1
1!
#26040625
0!
#26082290
b100110101 1
1)
09
1!
#26123955
0!
#26165620
0:
0)
b100110110 1
1!
#26207285
0!
#26248950
b100110111 1
1)
1!
#26290615
0!
#26332280
0)
b100111000 1
1!
#26373945
0!
#26415610
b100111001 1
1)
1!
#26457275
0!
#26498940
0)
b100111010 1
1!
#26540605
0!
#26582270
b100111011 1
1)
1!
#26623935
0!
#26665600
0)
b100111100 1
1!
#26707265
0!
#26748930
b100111101 1
1)
1!
#26790595
0!
#26832260
0)
b100111110 1
1!
#26873925
0!
#26915590
b100111111 1
1)
1!
#26957255
0!
#26998920
0)
b101000000 1
1!
#27040585
0!
#27082250
b101000001 1
1)
1!
#27123915
0!
#27165580
0)
b101000010 1
1!
#27207245
0!
#27248910
b101000011 1
1)
1!
#27290575
0!
#27332240
0)
b101000100 1
1!
#27373905
0!
#27415570
b101000101 1
1)
1!
#27457235
0!
#27498900
0)
b101000110 1
1!
#27540565
0!
#27582230
b101000111 1
1)
1!
#27623895
0!
#27665560
0)
b101001000 1
1!
#27707225
0!
#27748890
b101001001 1
1)
1!
#27790555
0!
#27832220
0)
b101001010 1
1!
#27873885
0!
#27915550
b101001011 1
1)
1!
#27957215
0!
#27998880
0)
b101001100 1
1!
#28040545
0!
#28082210
b101001101 1
1)
1!
#28123875
0!
#28165540
0)
b101001110 1
1!
#28207205
0!
#28248870
b101001111 1
1)
1!
#28290535
0!
#28332200
0)
b101010000 1
1!
#28373865
0!
#28415530
b101010001 1
1)
1!
#28457195
0!
#28498860
0)
b101010010 1
1!
#28540525
0!
#28582190
b101010011 1
1)
1!
#28623855
0!
#28665520
0)
b101010100 1
1!
#28707185
0!
#28748850
b101010101 1
1)
1!
#28790515
0!
#28832180
0)
b101010110 1
1!
#28873845
0!
#28915510
b101010111 1
1)
1!
#28957175
0!
#28998840
0)
b101011000 1
1!
#29040505
0!
#29082170
b101011001 1
1)
1!
#29123835
0!
#29165500
0)
b101011010 1
1!
#29207165
0!
#29248830
b101011011 1
1)
1!
#29290495
0!
#29332160
0)
b101011100 1
1!
#29373825
0!
#29415490
b101011101 1
1)
1!
#29457155
0!
#29498820
0)
b101011110 1
1!
#29540485
0!
#29582150
b101011111 1
1)
1!
#29623815
0!
#29665480
0)
b101100000 1
1!
#29707145
0!
#29748810
b101100001 1
1)
1!
#29790475
0!
#29832140
0)
b101100010 1
1!
#29873805
0!
#29915470
b101100011 1
1)
1!
#29957135
0!
#29998800
0)
b101100100 1
1!
#30040465
0!
#30082130
b101100101 1
1)
1!
#30123795
0!
#30165460
0)
b101100110 1
1!
#30207125
0!
#30248790
b101100111 1
1)
1!
#30290455
0!
#30332120
0)
b101101000 1
1!
#30373785
0!
#30415450
b101101001 1
1)
1!
#30457115
0!
#30498780
0)
b101101010 1
1!
#30540445
0!
#30582110
b101101011 1
1)
1!
#30623775
0!
#30665440
0)
b101101100 1
1!
#30707105
0!
#30748770
b101101101 1
1)
1!
#30790435
0!
#30832100
0)
b101101110 1
1!
#30873765
0!
#30915430
b101101111 1
1)
1!
#30916630
1&
#30957095
0!
#30998760
18
0)
b101110000 1
1!
#31040425
0!
#31082090
1(
b101110001 1
1)
19
1!
#31123755
0!
#31165420
0(
1:
0)
b11 2
b101110010 1
1!
#31207085
0!
#31248750
b101110011 1
1)
1!
#31290415
0!
#31332080
0)
b101110100 1
1!
#31373745
0!
#31415410
b101110101 1
1)
1!
#31457075
0!
#31498740
0)
b101110110 1
1!
#31540405
0!
#31582070
b101110111 1
1)
1!
#31623735
0!
#31665400
0)
b101111000 1
1!
#31707065
0!
#31748730
b101111001 1
1)
1!
#31790395
0!
#31832060
0)
b101111010 1
1!
#31873725
0!
#31915390
b101111011 1
1)
1!
#31957055
0!
#31998720
0)
b101111100 1
1!
#32040385
0!
#32082050
b101111101 1
1)
1!
#32123715
0!
#32165380
0)
b101111110 1
1!
#32207045
0!
#32248710
b101111111 1
1)
1!
#32290375
0!
#32332040
0)
b110000000 1
1!
#32373705
0!
#32415370
b110000001 1
1)
1!
#32457035
0!
#32498700
0)
b110000010 1
1!
#32540365
0!
#32582030
b110000011 1
1)
1!
#32623695
0!
#32665360
0)
b110000100 1
1!
#32707025
0!
#32748690
b110000101 1
1)
1!
#32790355
0!
#32832020
0)
b110000110 1
1!
#32873685
0!
#32915350
b110000111 1
1)
1!
#32957015
0!
#32998680
0)
b110001000 1
1!
#33040345
0!
#33082010
b110001001 1
1)
1!
#33123675
0!
#33165340
0)
b110001010 1
1!
#33207005
0!
#33248670
b110001011 1
1)
1!
#33290335
0!
#33332000
0)
b110001100 1
1!
#33373665
0!
#33415330
b110001101 1
1)
1!
#33456995
0!
#33498660
0)
b110001110 1
1!
#33540325
0!
#33581990
b110001111 1
1)
1!
#33623655
0!
#33665320
0)
b110010000 1
1!
#33706985
0!
#33748650
b110010001 1
1)
1!
#33790315
0!
#33831980
0)
b110010010 1
1!
#33873645
0!
#33915310
b110010011 1
1)
1!
#33956975
0!
#33998640
0)
b110010100 1
1!
#34040305
0!
#34081970
b110010101 1
1)
1!
#34123635
0!
#34165300
0)
b110010110 1
1!
#34206965
0!
#34248630
b110010111 1
1)
1!
#34290295
0!
#34331960
0)
b110011000 1
1!
#34373625
0!
#34415290
b110011001 1
1)
1!
#34456955
0!
#34498620
0)
b110011010 1
1!
#34540285
0!
#34581950
b110011011 1
1)
1!
#34623615
0!
#34665280
0)
b110011100 1
1!
#34706945
0!
#34748610
b110011101 1
1)
1!
#34790275
0!
#34831940
0)
b110011110 1
1!
#34873605
0!
#34915270
b110011111 1
1)
1!
#34956935
0!
#34998600
0)
b110100000 1
1!
#35040265
0!
#35081930
b110100001 1
1)
1!
#35123595
0!
#35165260
0)
b110100010 1
1!
#35206925
0!
#35248590
b110100011 1
1)
1!
#35290255
0!
#35331920
0)
b110100100 1
1!
#35373585
0!
#35415250
b110100101 1
1)
1!
#35456915
0!
#35498580
0)
b110100110 1
1!
#35540245
0!
#35581910
b110100111 1
1)
1!
#35623575
0!
#35665240
0)
b110101000 1
1!
#35706905
0!
#35748570
b110101001 1
1)
1!
#35790235
0!
#35831900
0)
b110101010 1
1!
#35873565
0!
#35915230
b110101011 1
1)
1!
#35916630
0&
#35956895
0!
#35998560
08
0)
b110101100 1
1!
#36040225
0!
#36081890
b110101101 1
1)
09
1!
#36123555
0!
#36165220
0:
0)
b110101110 1
1!
#36206885
0!
#36248550
b110101111 1
1)
1!
#36290215
0!
#36331880
0)
b110110000 1
1!
#36373545
0!
#36415210
b110110001 1
1)
1!
#36456875
0!
#36498540
0)
b110110010 1
1!
#36540205
0!
#36581870
b110110011 1
1)
1!
#36623535
0!
#36665200
0)
b110110100 1
1!
#36706865
0!
#36748530
b110110101 1
1)
1!
#36790195
0!
#36831860
0)
b110110110 1
1!
#36873525
0!
#36915190
b110110111 1
1)
1!
#36956855
0!
#36998520
0)
b110111000 1
1!
#37040185
0!
#37081850
b110111001 1
1)
1!
#37123515
0!
#37165180
0)
b110111010 1
1!
#37206845
0!
#37248510
b110111011 1
1)
1!
#37290175
0!
#37331840
0)
b110111100 1
1!
#37373505
0!
#37415170
b110111101 1
1)
1!
#37456835
0!
#37498500
0)
b110111110 1
1!
#37540165
0!
#37581830
b110111111 1
1)
1!
#37623495
0!
#37665160
0)
b111000000 1
1!
#37706825
0!
#37748490
b111000001 1
1)
1!
#37790155
0!
#37831820
0)
b111000010 1
1!
#37873485
0!
#37915150
b111000011 1
1)
1!
#37956815
0!
#37998480
0)
b111000100 1
1!
#38040145
0!
#38081810
b111000101 1
1)
1!
#38123475
0!
#38165140
0)
b111000110 1
1!
#38206805
0!
#38248470
b111000111 1
1)
1!
#38290135
0!
#38331800
0)
b111001000 1
1!
#38373465
0!
#38415130
b111001001 1
1)
1!
#38456795
0!
#38498460
0)
b111001010 1
1!
#38540125
0!
