fpga/frequency_counter.v
`default_nettype none	
`timescale 1ns/1ps

module frequency_counter #(
	parameter UPDATE_PERIOD = 1200 - 1,
	parameter BITS = 12
)
(
	input wire 				clk,
	input wire 				reset,
	input wire 				signal,

	input wire [BITS-1:0] 	period,
	input wire 				period_load,

	output wire [6:0] 		segments,
	output wire 			digit, 

	// debug wires
	output wire [1:0] 		dbg_state,		// state machine 
	output wire [2:0] 		dbg_clk_count, 	// top 3 bits of clk counter
	output wire [2:0] 		dbg_edge_count
);
	
	// debug assigns
	assign dbg_state = state;
	assign dbg_clk_count = clk_counter[BITS-1:BITS-3];
	assign dbg_edge_count = edge_counter[6:4];

	reg [BITS-1:0] update_period; // holds the number of edges for frequency measurement

	reg [6:0] edge_counter; // 2^7 is 128, can count up to 99

	reg [BITS-1:0] clk_counter; // keeps track of clocks in the counting period

	reg [3:0] unit_count, ten_count;

	reg update_digits; // toggles the loading signal for the seven pmod display

	wire leading_edge_detect;

	edge_detect edge_detect0(.signal(signal), .clk(clk), .leading_edge_detect(leading_edge_detect));

	always @(posedge clk) begin
		if (reset) 
			update_period <= UPDATE_PERIOD;
		else if (period_load) 
			update_period <= period; // sets a new period when period_load is high
	end

	// STATE machine register, holds 3 states
	reg [1:0] state;

	localparam STATE_COUNT	= 0;
	localparam STATE_TENS 	= 1;
	localparam STATE_UNITS 	= 2;

	always @(posedge clk) begin
		if (reset) begin
			clk_counter 	<= 0;
			edge_counter 	<= 0;
			unit_count	 	<= 0;
			ten_count 		<= 0;
			update_digits 	<= 0;
			state 			<= STATE_COUNT;

		end else begin
			case(state)
				STATE_COUNT : begin
					update_digits 	<= 0;
					clk_counter 	<= clk_counter + 1'b1;

					if(leading_edge_detect) 
						edge_counter <= edge_counter + 1'b1;

					if(clk_counter >= update_period) begin
						clk_counter <= 0; 
						unit_count 	<= 0; 
						ten_count	<= 0; 
						state 		<= STATE_TENS; 
					end
				end

				STATE_TENS : begin
					if (edge_counter < 7'd10)
						state <= STATE_UNITS;
					else begin
						edge_counter <= edge_counter - 7'd10;
						ten_count <= ten_count + 1'b1;
					end
				end

				STATE_UNITS : begin
					unit_count 		<= edge_counter;
					update_digits	<= 1'b1;
					edge_counter 	<= 0;
					state 			<= STATE_COUNT;
				end

				default : state <= STATE_COUNT;
				
			endcase			
		end
	end

	seven_segment seven_segment0(.clk(clk), .reset(reset), .ten_count(ten_count), .unit_count(unit_count), .load(update_digits), .segments(segments), .digit(digit));

endmodule

module edge_detect (
    input wire signal,
    input wire clk,
    output wire leading_edge_detect
);

    reg q0, q1, q2;

    always @(posedge clk) begin
       q0 <= signal;
       q1 <= q0;
       q2 <= q1;
    end

    assign leading_edge_detect = q1 & (q2 != q1);   // leaving the leading edges

endmodule

module seven_segment (

    input wire 			clk,
    input wire  		reset,
    input wire  		load,
    input wire [3:0]    ten_count,
    input wire [3:0] 	unit_count,
    output reg [6:0] 	segments,
    output reg			digit    	// digit selector
);

    reg [3:0] ten_count_reg, unit_count_reg;
    wire [3:0] decode;

    always @(posedge clk) begin
		if(reset) begin
			ten_count_reg <= 0;
			unit_count_reg <= 0;
			digit <= 0;
		end else begin
			if(load) begin
				ten_count_reg  <= ten_count;
				unit_count_reg <= unit_count;
			end

			digit <= !digit; 

		end
    end 

    assign decode = digit ? ten_count_reg: unit_count_reg;

    // why is this indented?

   	always @(*) begin
            case(decode)
            //                7654321
            0:  segments = 7'b0111111;
            1:  segments = 7'b0000110;
            2:  segments = 7'b1011011;
            3:  segments = 7'b1001111;
            4:  segments = 7'b1100110;
            5:  segments = 7'b1101101;
            6:  segments = 7'b1111100;
            7:  segments = 7'b0000111;
            8:  segments = 7'b1111111;
            9:  segments = 7'b1100111;
            default:    
                segments = 7'b0000000;
            endcase
	end


endmodule

seven_segment.vcd
$date
	Fri May 24 01:28:43 2024
$end
$version
	Icarus Verilog
$end
$timescale
	1ns
$end
$scope module seven_segment $end
$var wire 1 ! clk $end
$var wire 1 " load $end
$var wire 1 # reset $end
$var wire 4 $ ten_count [3:0] $end
$var wire 4 % unit_count [3:0] $end
$var wire 4 & decode [3:0] $end
$var reg 1 ' digit $end
$var reg 7 ( segments [6:0] $end
$var reg 4 ) ten_count_reg [3:0] $end
$var reg 4 * unit_count_reg [3:0] $end
$upscope $end
$enddefinitions $end
$comment Show the parameter values. $end
$dumpall
$end
#0
$dumpvars
b0 *
b0 )
b111111 (
0'
b0 &
bz %
bz $
1#
z"
1!
$end
#5000
0!
#10000
1!
#15000
0!
#20000
1!
#25000
0!
#30000
1!
#35000
0!
#40000
0"
0#
1!
#45000
0!
#50000
1'
1!
#55000
0!
#60000
0'
1!
#65000
0!
#70000
1'
1!
#75000
0!
#80000
0'
1!
#85000
0!
#90000
1"
b0 %
b0 $
1'
1!
#95000
0!
#100000
0"
0'
1!
#105000
0!
#110000
1'
1!
#115000
0!
#120000
0'
1!
#125000
0!
#130000
1'
1!
#135000
0!
#140000
1"
b1 %
0'
1!
#145000
0!
#150000
0"
1'
b1 *
1!
#155000
0!
#160000
b110 (
b1 &
0'
1!
#165000
0!
#170000
b111111 (
b0 &
1'
1!
#175000
0!
#180000
1"
b10 %
b110 (
b1 &
0'
1!
#185000
0!
#190000
0"
b111111 (
b0 &
1'
b10 *
1!
#195000
0!
#200000
b1011011 (
b10 &
0'
1!
#205000
0!
#210000
b111111 (
b0 &
1'
1!
#215000
0!
#220000
1"
b11 %
b1011011 (
b10 &
0'
1!
#225000
0!
#230000
0"
b111111 (
b0 &
1'
b11 *
1!
#235000
0!
#240000
b1001111 (
b11 &
0'
1!
#245000
0!
#250000
b111111 (
b0 &
1'
1!
#255000
0!
#260000
1"
b100 %
b1001111 (
b11 &
0'
1!
#265000
0!
#270000
0"
b111111 (
b0 &
1'
b100 *
1!
#275000
0!
#280000
b1100110 (
b100 &
0'
1!
#285000
0!
#290000
b111111 (
b0 &
1'
1!
#295000
0!
#300000
1"
b101 %
b1100110 (
b100 &
0'
1!
#305000
0!
#310000
0"
b111111 (
b0 &
1'
b101 *
1!
#315000
0!
#320000
b1101101 (
b101 &
0'
1!
#325000
0!
#330000
b111111 (
b0 &
1'
1!
#335000
0!
#340000
1"
b110 %
b1101101 (
b101 &
0'
1!
#345000
0!
#350000
0"
b111111 (
b0 &
1'
b110 *
1!
#355000
0!
#360000
b1111100 (
b110 &
0'
1!
#365000
0!
#370000
b111111 (
b0 &
1'
1!
#375000
0!
#380000
1"
b111 %
b1111100 (
b110 &
0'
1!
#385000
0!
#390000
0"
b111111 (
b0 &
1'
b111 *
1!
#395000
0!
#400000
b111 (
b111 &
0'
1!
#405000
0!
#410000
b111111 (
b0 &
1'
1!
#415000
0!
#420000
1"
b1000 %
b111 (
b111 &
0'
1!
#425000
0!
#430000
0"
b111111 (
b0 &
1'
b1000 *
1!
#435000
0!
#440000
b1111111 (
b1000 &
0'
1!
#445000
0!
#450000
b111111 (
b0 &
1'
1!
#455000
0!
#460000
1"
b1001 %
b1111111 (
b1000 &
0'
1!
#465000
0!
#470000
0"
b111111 (
b0 &
1'
b1001 *
1!
#475000
0!
#480000
b1100111 (
b1001 &
0'
1!
#485000
0!
#490000
b111111 (
b0 &
1'
1!
#495000
0!
#500000
1"
b0 %
b1 $
b1100111 (
b1001 &
0'
1!
#505000
0!
#510000
0"
b110 (
b1 &
1'
b0 *
b1 )
1!
#515000
0!
#520000
b111111 (
b0 &
0'
1!
#525000
0!
#530000
b110 (
b1 &
1'
1!
#535000
0!
#540000
1"
b1 %
b111111 (
b0 &
0'
1!
#545000
0!
#550000
0"
b110 (
b1 &
1'
b1 *
1!
#555000
0!
#560000
0'
1!
#565000
0!
#570000
1'
1!
#575000
0!
#580000
1"
b10 %
0'
1!
#585000
0!
#590000
0"
1'
b10 *
1!
#595000
0!
#600000
b1011011 (
b10 &
0'
1!
#605000
0!
#610000
b110 (
b1 &
1'
1!
#615000
0!
#620000
1"
b11 %
b1011011 (
b10 &
0'
1!
#625000
0!
#630000
0"
b110 (
b1 &
1'
b11 *
1!
#635000
0!
#640000
b1001111 (
b11 &
0'
1!
#645000
0!
#650000
b110 (
b1 &
1'
1!
#655000
0!
#660000
1"
b100 %
b1001111 (
b11 &
0'
1!
#665000
0!
#670000
0"
b110 (
b1 &
1'
b100 *
1!
#675000
0!
#680000
b1100110 (
b100 &
0'
1!
#685000
0!
#690000
b110 (
b1 &
1'
1!
#695000
0!
#700000
1"
b101 %
b1100110 (
b100 &
0'
1!
#705000
0!
#710000
0"
b110 (
b1 &
1'
b101 *
1!
#715000
0!
#720000
b1101101 (
b101 &
0'
1!
#725000
0!
#730000
b110 (
b1 &
1'
1!
#735000
0!
#740000
1"
b110 %
b1101101 (
b101 &
0'
1!
#745000
0!
#750000
0"
b110 (
b1 &
1'
b110 *
1!
#755000
0!
#760000
b1111100 (
b110 &
0'
1!
#765000
0!
#770000
b110 (
b1 &
1'
1!
#775000
0!
#780000
1"
b111 %
b1111100 (
b110 &
0'
1!
#785000
0!
#790000
0"
b110 (
b1 &
1'
b111 *
1!
#795000
0!
#800000
b111 (
b111 &
0'
1!
#805000
0!
#810000
b110 (
b1 &
1'
1!
#815000
0!
#820000
1"
b1000 %
b111 (
b111 &
0'
1!
#825000
0!
#830000
0"
b110 (
b1 &
1'
b1000 *
1!
#835000
0!
#840000
b1111111 (
b1000 &
0'
1!
#845000
0!
#850000
b110 (
b1 &
1'
1!
#855000
0!
#860000
1"
b1001 %
b1111111 (
b1000 &
0'
1!
#865000
0!
#870000
0"
b110 (
b1 &
1'
b1001 *
1!
#875000
0!
#880000
b1100111 (
b1001 &
0'
1!
#885000
0!
#890000
b110 (
b1 &
1'
1!
#895000
0!
#900000
1"
b0 %
b10 $
b1100111 (
b1001 &
0'
1!
#905000
0!
#910000
0"
b1011011 (
b10 &
1'
b0 *
b10 )
1!
#915000
0!
#920000
b111111 (
b0 &
0'
1!
#925000
0!
#930000
b1011011 (
b10 &
1'
1!
#935000
0!
#940000
1"
b1 %
b111111 (
b0 &
0'
1!
#945000
0!
#950000
0"
b1011011 (
b10 &
1'
b1 *
1!
#955000
0!
#960000
b110 (
b1 &
0'
1!
#965000
0!
#970000
b1011011 (
b10 &
1'
1!
#975000
0!
#980000
1"
b10 %
b110 (
b1 &
0'
1!
#985000
0!
#990000
0"
b1011011 (
b10 &
1'
b10 *
1!
#995000
0!
#1000000
0'
1!
#1005000
0!
#1010000
1'
1!
#1015000
0!
#1020000
1"
b11 %
0'
1!
#1025000
0!
#1030000
0"
1'
b11 *
1!
#1035000
0!
#1040000
b1001111 (
b11 &
0'
1!
#1045000
0!
#1050000
b1011011 (
b10 &
1'
1!
#1055000
0!
#1060000
1"
b100 %
b1001111 (
b11 &
0'
1!
#1065000
0!
#1070000
0"
b1011011 (
b10 &
1'
b100 *
1!
#1075000
0!
#1080000
b1100110 (
b100 &
0'
1!
#1085000
0!
#1090000
b1011011 (
b10 &
1'
1!
#1095000
0!
#1100000
1"
b101 %
b1100110 (
b100 &
0'
1!
#1105000
0!
#1110000
0"
b1011011 (
b10 &
1'
b101 *
1!
#1115000
0!
#1120000
b1101101 (
b101 &
0'
1!
#1125000
0!
#1130000
b1011011 (
b10 &
1'
1!
#1135000
0!
#1140000
1"
b110 %
b1101101 (
b101 &
0'
1!
#1145000
0!
#1150000
0"
b1011011 (
b10 &
1'
b110 *
1!
#1155000
0!
#1160000
b1111100 (
b110 &
0'
1!
#1165000
0!
#1170000
b1011011 (
b10 &
1'
1!
#1175000
0!
#1180000
1"
b111 %
b1111100 (
b110 &
0'
1!
#1185000
0!
#1190000
0"
b1011011 (
b10 &
1'
b111 *
1!
#1195000
0!
#1200000
b111 (
b111 &
0'
1!
#1205000
0!
#1210000
b1011011 (
b10 &
1'
1!
#1215000
0!
#1220000
1"
b1000 %
b111 (
b111 &
0'
1!
#1225000
0!
#1230000
0"
b1011011 (
b10 &
1'
b1000 *
1!
#1235000
0!
#1240000
b1111111 (
b1000 &
0'
1!
#1245000
0!
#1250000
b1011011 (
b10 &
1'
1!
#1255000
0!
#1260000
1"
b1001 %
b1111111 (
b1000 &
0'
1!
#1265000
0!
#1270000
0"
b1011011 (
b10 &
1'
b1001 *
1!
#1275000
0!
#1280000
b1100111 (
b1001 &
0'
1!
#1285000
0!
#1290000
b1011011 (
b10 &
1'
1!
#1295000
0!
#1300000
1"
b0 %
b11 $
b1100111 (
b1001 &
0'
1!
#1305000
0!
#1310000
0"
b1001111 (
b11 &
1'
b0 *
b11 )
1!
#1315000
0!
#1320000
b111111 (
b0 &
0'
1!
#1325000
0!
#1330000
b1001111 (
b11 &
1'
1!
#1335000
0!
#1340000
1"
b1 %
b111111 (
b0 &
0'
1!
#1345000
0!
#1350000
0"
b1001111 (
b11 &
1'
b1 *
1!
#1355000
0!
#1360000
b110 (
b1 &
0'
1!
#1365000
0!
#1370000
b1001111 (
b11 &
1'
1!
#1375000
0!
#1380000
1"
b10 %
b110 (
b1 &
0'
1!
#1385000
0!
#1390000
0"
b1001111 (
b11 &
1'
b10 *
1!
#1395000
0!
#1400000
b1011011 (
b10 &
0'
1!
#1405000
0!
#1410000
b1001111 (
b11 &
1'
1!
#1415000
0!
#1420000
1"
b11 %
b1011011 (
b10 &
0'
1!
#1425000
0!
#1430000
0"
b1001111 (
b11 &
1'
b11 *
1!
#1435000
0!
#1440000
0'
1!
#1445000
0!
#1450000
1'
1!
#1455000
0!
#1460000
1"
b100 %
0'
1!
#1465000
0!
#1470000
0"
1'
b100 *
1!
#1475000
0!
#1480000
b1100110 (
b100 &
0'
1!
#1485000
0!
#1490000
b1001111 (
b11 &
1'
1!
#1495000
0!
#1500000
1"
b101 %
b1100110 (
b100 &
0'
1!
#1505000
0!
#1510000
0"
b1001111 (
b11 &
1'
b101 *
1!
#1515000
0!
#1520000
b1101101 (
b101 &
0'
1!
#1525000
0!
#1530000
b1001111 (
b11 &
1'
1!
#1535000
0!
#1540000
1"
b110 %
b1101101 (
b101 &
0'
1!
#1545000
0!
#1550000
0"
b1001111 (
b11 &
1'
b110 *
1!
#1555000
0!
#1560000
b1111100 (
b110 &
0'
1!
#1565000
0!
#1570000
b1001111 (
b11 &
1'
1!
#1575000
0!
#1580000
1"
b111 %
b1111100 (
b110 &
0'
1!
#1585000
0!
#1590000
0"
b1001111 (
b11 &
1'
b111 *
1!
#1595000
0!
#1600000
b111 (
b111 &
0'
1!
#1605000
0!
#1610000
b1001111 (
b11 &
1'
1!
#1615000
0!
#1620000
1"
b1000 %
b111 (
b111 &
0'
1!
#1625000
0!
#1630000
0"
b1001111 (
b11 &
1'
b1000 *
1!
#1635000
0!
#1640000
b1111111 (
b1000 &
0'
1!
#1645000
0!
#1650000
b1001111 (
b11 &
1'
1!
#1655000
0!
#1660000
1"
b1001 %
b1111111 (
b1000 &
0'
1!
#1665000
0!
#1670000
0"
b1001111 (
b11 &
1'
b1001 *
1!
#1675000
0!
#1680000
b1100111 (
b1001 &
0'
1!
#1685000
0!
#1690000
b1001111 (
b11 &
1'
1!
#1695000
0!
#1700000
1"
b0 %
b100 $
b1100111 (
b1001 &
0'
1!
#1705000
0!
#1710000
0"
b1100110 (
b100 &
1'
b0 *
b100 )
1!
#1715000
0!
#1720000
b111111 (
b0 &
0'
1!
#1725000
0!
#1730000
b1100110 (
b100 &
1'
1!
#1735000
0!
#1740000
1"
b1 %
b111111 (
b0 &
0'
1!
#1745000
0!
#1750000
0"
b1100110 (
b100 &
1'
b1 *
1!
#1755000
0!
#1760000
b110 (
b1 &
0'
1!
#1765000
0!
#1770000
b1100110 (
b100 &
1'
1!
#1775000
0!
#1780000
1"
b10 %
b110 (
b1 &
0'
1!
#1785000
0!
#1790000
0"
b1100110 (
b100 &
1'
b10 *
1!
#1795000
0!
#1800000
b1011011 (
b10 &
0'
1!
#1805000
0!
#1810000
b1100110 (
b100 &
1'
1!
#1815000
0!
#1820000
1"
b11 %
b1011011 (
b10 &
0'
1!
#1825000
0!
#1830000
0"
b1100110 (
b100 &
1'
b11 *
1!
#1835000
0!
#1840000
b1001111 (
b11 &
0'
1!
#1845000
0!
#1850000
b1100110 (
b100 &
1'
1!
#1855000
0!
#1860000
1"
b100 %
b1001111 (
b11 &
0'
1!
#1865000
0!
#1870000
0"
b1100110 (
b100 &
1'
b100 *
1!
#1875000
0!
#1880000
0'
1!
#1885000
0!
#1890000
1'
1!
#1895000
0!
#1900000
1"
b101 %
0'
1!
#1905000
0!
#1910000
0"
1'
b101 *
1!
#1915000
0!
#1920000
b1101101 (
b101 &
0'
1!
#1925000
0!
#1930000
b1100110 (
b100 &
1'
1!
#1935000
0!
#1940000
1"
b110 %
b1101101 (
b101 &
0'
1!
#1945000
0!
#1950000
0"
b1100110 (
b100 &
1'
b110 *
1!
#1955000
0!
#1960000
b1111100 (
b110 &
0'
1!
#1965000
0!
#1970000
b1100110 (
b100 &
1'
1!
#1975000
0!
#1980000
1"
b111 %
b1111100 (
b110 &
0'
1!
#1985000
0!
#1990000
0"
b1100110 (
b100 &
1'
b111 *
1!
#1995000
0!
#2000000
b111 (
b111 &
0'
1!
#2005000
0!
#2010000
b1100110 (
b100 &
1'
1!
#2015000
0!
#2020000
1"
b1000 %
b111 (
b111 &
0'
1!
#2025000
0!
#2030000
0"
b1100110 (
b100 &
1'
b1000 *
1!
#2035000
0!
#2040000
b1111111 (
b1000 &
0'
1!
#2045000
0!
#2050000
b1100110 (
b100 &
1'
1!
#2055000
0!
#2060000
1"
b1001 %
b1111111 (
b1000 &
0'
1!
#2065000
0!
#2070000
0"
b1100110 (
b100 &
1'
b1001 *
1!
#2075000
0!
#2080000
b1100111 (
b1001 &
0'
1!
#2085000
0!
#2090000
b1100110 (
b100 &
1'
1!
#2095000
0!
#2100000
1"
b0 %
b101 $
b1100111 (
b1001 &
0'
1!
#2105000
0!
#2110000
0"
b1101101 (
b101 &
1'
b0 *
b101 )
1!
#2115000
0!
#2120000
b111111 (
b0 &
0'
1!
#2125000
0!
#2130000
b1101101 (
b101 &
1'
1!
#2135000
0!
#2140000
1"
b1 %
b111111 (
b0 &
0'
1!
#2145000
0!
#2150000
0"
b1101101 (
b101 &
1'
b1 *
1!
#2155000
0!
#2160000
b110 (
b1 &
0'
1!
#2165000
0!
#2170000
b1101101 (
b101 &
1'
1!
#2175000
0!
#2180000
1"
b10 %
b110 (
b1 &
0'
1!
#2185000
0!
#2190000
0"
b1101101 (
b101 &
1'
b10 *
1!
#2195000
0!
#2200000
b1011011 (
b10 &
0'
1!
#2205000
0!
#2210000
b1101101 (
b101 &
1'
1!
#2215000
0!
#2220000
1"
b11 %
b1011011 (
b10 &
0'
1!
#2225000
0!
#2230000
0"
b1101101 (
b101 &
1'
b11 *
1!
#2235000
0!
#2240000
b1001111 (
b11 &
0'
1!
#2245000
0!
#2250000
b1101101 (
b101 &
1'
1!
#2255000
0!
#2260000
1"
b100 %
b1001111 (
b11 &
0'
1!
#2265000
0!
#2270000
0"
b1101101 (
b101 &
1'
b100 *
1!
#2275000
0!
#2280000
b1100110 (
b100 &
0'
1!
#2285000
0!
#2290000
b1101101 (
b101 &
1'
1!
#2295000
0!
#2300000
1"
b101 %
b1100110 (
b100 &
0'
1!
#2305000
0!
#2310000
0"
b1101101 (
b101 &
1'
b101 *
1!
#2315000
0!
#2320000
0'
1!
#2325000
0!
#2330000
1'
1!
#2335000
0!
#2340000
1"
b110 %
0'
1!
#2345000
0!
#2350000
0"
1'
b110 *
1!
#2355000
0!
#2360000
b1111100 (
b110 &
0'
1!
#2365000
0!
#2370000
b1101101 (
b101 &
1'
1!
#2375000
0!
#2380000
1"
b111 %
b1111100 (
b110 &
0'
1!
#2385000
0!
#2390000
0"
b1101101 (
b101 &
1'
b111 *
1!
#2395000
0!
#2400000
b111 (
b111 &
0'
1!
#2405000
0!
#2410000
b1101101 (
b101 &
1'
1!
#2415000
0!
#2420000
1"
b1000 %
b111 (
b111 &
0'
1!
#2425000
0!
#2430000
0"
b1101101 (
b101 &
1'
b1000 *
1!
#2435000
0!
#2440000
b1111111 (
b1000 &
0'
1!
#2445000
0!
#2450000
b1101101 (
b101 &
1'
1!
#2455000
0!
#2460000
1"
b1001 %
b1111111 (
b1000 &
0'
1!
#2465000
0!
#2470000
0"
b1101101 (
b101 &
1'
b1001 *
1!
#2475000
0!
#2480000
b1100111 (
b1001 &
0'
1!
#2485000
0!
#2490000
b1101101 (
b101 &
1'
1!
#2495000
0!
#2500000
1"
b0 %
b110 $
b1100111 (
b1001 &
0'
1!
#2505000
0!
#2510000
0"
b1111100 (
b110 &
1'
b0 *
b110 )
1!
#2515000
0!
#2520000
b111111 (
b0 &
0'
1!
#2525000
0!
#2530000
b1111100 (
b110 &
1'
1!
#2535000
0!
#2540000
1"
b1 %
b111111 (
b0 &
0'
1!
#2545000
0!
#2550000
0"
b1111100 (
b110 &
1'
b1 *
1!
#2555000
0!
#2560000
b110 (
b1 &
0'
1!
#2565000
0!
#2570000
b1111100 (
b110 &
1'
1!
#2575000
0!
#2580000
1"
b10 %
b110 (
b1 &
0'
1!
#2585000
0!
#2590000
0"
b1111100 (
b110 &
1'
b10 *
1!
#2595000
0!
#2600000
b1011011 (
b10 &
0'
1!
#2605000
0!
#2610000
b1111100 (
b110 &
1'
1!
#2615000
0!
#2620000
1"
b11 %
b1011011 (
b10 &
0'
1!
#2625000
0!
#2630000
0"
b1111100 (
b110 &
1'
b11 *
1!
#2635000
0!
#2640000
b1001111 (
b11 &
0'
1!
#2645000
0!
#2650000
b1111100 (
b110 &
1'
1!
#2655000
0!
#2660000
1"
b100 %
b1001111 (
b11 &
0'
1!
#2665000
0!
#2670000
0"
b1111100 (
b110 &
1'
b100 *
1!
#2675000
0!
#2680000
b1100110 (
b100 &
0'
1!
#2685000
0!
#2690000
b1111100 (
b110 &
1'
1!
#2695000
0!
#2700000
1"
b101 %
b1100110 (
b100 &
0'
1!
#2705000
0!
#2710000
0"
b1111100 (
b110 &
1'
b101 *
1!
#2715000
0!
#2720000
b1101101 (
b101 &
0'
1!
#2725000
0!
#2730000
b1111100 (
b110 &
1'
1!
#2735000
0!
#2740000
1"
b110 %
b1101101 (
b101 &
0'
1!
#2745000
0!
#2750000
0"
b1111100 (
b110 &
1'
b110 *
1!
#2755000
0!
#2760000
0'
1!
#2765000
0!
#2770000
1'
1!
#2775000
0!
#2780000
1"
b111 %
0'
1!
#2785000
0!
#2790000
0"
1'
b111 *
1!
#2795000
0!
#2800000
b111 (
b111 &
0'
1!
#2805000
0!
#2810000
b1111100 (
b110 &
1'
1!
#2815000
0!
#2820000
1"
b1000 %
b111 (
b111 &
0'
1!
#2825000
0!
#2830000
0"
b1111100 (
b110 &
1'
b1000 *
1!
#2835000
0!
#2840000
b1111111 (
b1000 &
0'
1!
#2845000
0!
#2850000
b1111100 (
b110 &
1'
1!
#2855000
0!
#2860000
1"
b1001 %
b1111111 (
b1000 &
0'
1!
#2865000
0!
#2870000
0"
b1111100 (
b110 &
1'
b1001 *
1!
#2875000
0!
#2880000
b1100111 (
b1001 &
0'
1!
#2885000
0!
#2890000
b1111100 (
b110 &
1'
1!
#2895000
0!
#2900000
1"
b0 %
b111 $
b1100111 (
b1001 &
0'
1!
#2905000
0!
#2910000
0"
b111 (
b111 &
1'
b0 *
b111 )
1!
#2915000
0!
#2920000
b111111 (
b0 &
0'
1!
#2925000
0!
#2930000
b111 (
b111 &
1'
1!
#2935000
0!
#2940000
1"
b1 %
b111111 (
b0 &
0'
1!
#2945000
0!
#2950000
0"
b111 (
b111 &
1'
b1 *
1!
#2955000
0!
#2960000
b110 (
b1 &
0'
1!
#2965000
0!
#2970000
b111 (
b111 &
1'
1!
#2975000
0!
#2980000
1"
b10 %
b110 (
b1 &
0'
1!
#2985000
0!
#2990000
0"
b111 (
b111 &
1'
b10 *
1!
#2995000
0!
#3000000
b1011011 (
b10 &
0'
1!
#3005000
0!
#3010000
b111 (
b111 &
1'
1!
#3015000
0!
#3020000
1"
b11 %
b1011011 (
b10 &
0'
1!
#3025000
0!
#3030000
0"
b111 (
b111 &
1'
b11 *
1!
#3035000
0!
#3040000
b1001111 (
b11 &
0'
1!
#3045000
0!
#3050000
b111 (
b111 &
1'
1!
#3055000
0!
#3060000
1"
b100 %
b1001111 (
b11 &
0'
1!
#3065000
0!
#3070000
0"
b111 (
b111 &
1'
b100 *
1!
#3075000
0!
#3080000
b1100110 (
b100 &
0'
1!
#3085000
0!
#3090000
b111 (
b111 &
1'
1!
#3095000
0!
#3100000
1"
b101 %
b1100110 (
b100 &
0'
1!
#3105000
0!
#3110000
0"
b111 (
b111 &
1'
b101 *
1!
#3115000
0!
#3120000
b1101101 (
b101 &
0'
1!
#3125000
0!
#3130000
b111 (
b111 &
1'
1!
#3135000
0!
#3140000
1"
b110 %
b1101101 (
b101 &
0'
1!
#3145000
0!
#3150000
0"
b111 (
b111 &
1'
b110 *
1!
#3155000
0!
#3160000
b1111100 (
b110 &
0'
1!
#3165000
0!
#3170000
b111 (
b111 &
1'
1!
#3175000
0!
#3180000
1"
b111 %
b1111100 (
b110 &
0'
1!
#3185000
0!
#3190000
0"
b111 (
b111 &
1'
b111 *
1!
#3195000
0!
#3200000
0'
1!
#3205000
0!
#3210000
1'
1!
#3215000
0!
#3220000
1"
b1000 %
0'
1!
#3225000
0!
#3230000
0"
1'
b1000 *
1!
#3235000
0!
#3240000
b1111111 (
b1000 &
0'
1!
#3245000
0!
#3250000
b111 (
b111 &
1'
1!
#3255000
0!
#3260000
1"
b1001 %
b1111111 (
b1000 &
0'
1!
#3265000
0!
#3270000
0"
b111 (
b111 &
1'
b1001 *
1!
#3275000
0!
#3280000
b1100111 (
b1001 &
0'
1!
#3285000
0!
#3290000
b111 (
b111 &
1'
1!
#3295000
0!
#3300000
1"
b0 %
b1000 $
b1100111 (
b1001 &
0'
1!
#3305000
0!
#3310000
0"
b1111111 (
b1000 &
1'
b0 *
b1000 )
1!
#3315000
0!
#3320000
b111111 (
b0 &
0'
1!
#3325000
0!
#3330000
b1111111 (
b1000 &
1'
1!
#3335000
0!
#3340000
1"
b1 %
b111111 (
b0 &
0'
1!
#3345000
0!
#3350000
0"
b1111111 (
b1000 &
1'
b1 *
1!
#3355000
0!
#3360000
b110 (
b1 &
0'
1!
#3365000
0!
#3370000
b1111111 (
b1000 &
1'
1!
#3375000
0!
#3380000
1"
b10 %
b110 (
b1 &
0'
1!
#3385000
0!
#3390000
0"
b1111111 (
b1000 &
1'
b10 *
1!
#3395000
0!
#3400000
b1011011 (
b10 &
0'
1!
#3405000
0!
#3410000
b1111111 (
b1000 &
1'
1!
#3415000
0!
#3420000
1"
b11 %
b1011011 (
b10 &
0'
1!
#3425000
0!
#3430000
0"
b1111111 (
b1000 &
1'
b11 *
1!
#3435000
0!
#3440000
b1001111 (
b11 &
0'
1!
#3445000
0!
#3450000
b1111111 (
b1000 &
1'
1!
#3455000
0!
#3460000
1"
b100 %
b1001111 (
b11 &
0'
1!
#3465000
0!
#3470000
0"
b1111111 (
b1000 &
1'
b100 *
1!
#3475000
0!
#3480000
b1100110 (
b100 &
0'
1!
#3485000
0!
#3490000
b1111111 (
b1000 &
1'
1!
#3495000
0!
#3500000
1"
b101 %
b1100110 (
b100 &
0'
1!
#3505000
0!
#3510000
0"
b1111111 (
b1000 &
1'
b101 *
1!
#3515000
0!
#3520000
b1101101 (
b101 &
0'
1!
#3525000
0!
#3530000
b1111111 (
b1000 &
1'
1!
#3535000
0!
#3540000
1"
b110 %
b1101101 (
b101 &
0'
1!
#3545000
0!
#3550000
0"
b1111111 (
b1000 &
1'
b110 *
1!
#3555000
0!
#3560000
b1111100 (
b110 &
0'
1!
#3565000
0!
#3570000
b1111111 (
b1000 &
1'
1!
#3575000
0!
#3580000
1"
b111 %
b1111100 (
b110 &
0'
1!
#3585000
0!
#3590000
0"
b1111111 (
b1000 &
1'
b111 *
1!
#3595000
0!
#3600000
b111 (
b111 &
0'
1!
#3605000
0!
#3610000
b1111111 (
b1000 &
1'
1!
#3615000
0!
#3620000
1"
b1000 %
b111 (
b111 &
0'
1!
#3625000
0!
#3630000
0"
b1111111 (
b1000 &
1'
b1000 *
1!
#3635000
0!
#3640000
0'
1!
#3645000
0!
#3650000
1'
1!
#3655000
0!
#3660000
1"
b1001 %
0'
1!
#3665000
0!
#3670000
0"
1'
b1001 *
1!
#3675000
0!
#3680000
b1100111 (
b1001 &
0'
1!
#3685000
0!
#3690000
b1111111 (
b1000 &
1'
1!
#3695000
0!
#3700000
1"
b0 %
b1001 $
b1100111 (
b1001 &
0'
1!
#3705000
0!
#3710000
0"
1'
b0 *
b1001 )
1!
#3715000
0!
#3720000
b111111 (
b0 &
0'
1!
#3725000
0!
#3730000
b1100111 (
b1001 &
1'
1!
#3735000
0!
#3740000
1"
b1 %
b111111 (
b0 &
0'
1!
#3745000
0!
#3750000
0"
b1100111 (
b1001 &
1'
b1 *
1!
#3755000
0!
#3760000
b110 (
b1 &
0'
1!
#3765000
0!
#3770000
b1100111 (
b1001 &
1'
1!
#3775000
0!
#3780000
1"
b10 %
b110 (
b1 &
0'
1!
#3785000
0!
#3790000
0"
b1100111 (
b1001 &
1'
b10 *
1!
#3795000
0!
#3800000
b1011011 (
b10 &
0'
1!
#3805000
0!
#3810000
b1100111 (
b1001 &
1'
1!
#3815000
0!
#3820000
1"
b11 %
b1011011 (
b10 &
0'
1!
#3825000
0!
#3830000
0"
b1100111 (
b1001 &
1'
b11 *
1!
#3835000
0!
#3840000
b1001111 (
b11 &
0'
1!
#3845000
0!
#3850000
b1100111 (
b1001 &
1'
1!
#3855000
0!
#3860000
1"
b100 %
b1001111 (
b11 &
0'
1!
#3865000
0!
